lightweight_charts_server/__init__.py
lightweight_charts_server/display.py
lightweight_charts_server/ftype.py
lightweight_charts_server/server.py
lightweight_charts_server/system.py
lightweight_charts_server/template.py
lightweight_charts_server/static/default.css
lightweight_charts_server/static/index.html
lightweight_charts_server/static/index.js
lightweight_charts_server/static/styles.css
lightweight_charts_server/static/asset/arrow.png
lightweight_charts_server/static/asset/favicon.ico
lightweight_charts_server/static/build/bundle.js
lightweight_charts_server/static/build/lightweight-charts.js
lightweight_charts_server/static/build/pywebview.js
lightweight_charts_server-0.2.4.dist-info/METADATA
lightweight_charts_server-0.2.4.dist-info/WHEEL
lightweight_charts_server-0.2.4.dist-info/top_level.txt
lightweight_charts_server-0.2.4.dist-info/RECORD
