Metadata-Version: 2.1
Name: lightweight-charts-server
Version: 0.2.4
Summary: lightweight-chart custom python server
Author-email: Won JeongHoo <clomia.sig@gmail.com>
Project-URL: Homepage, https://github.com/vegaxholdings/lightweight-charts-server
Classifier: Programming Language :: Python :: 3
Classifier: License :: OSI Approved :: MIT License
Classifier: Operating System :: OS Independent
Requires-Python: >=3.10
Requires-Dist: fastapi==0.112.0
Requires-Dist: uvicorn[standard]
Requires-Dist: lightweight-charts==2.0.1
Requires-Dist: psutil==6.0.0
Requires-Dist: portalocker==2.10.1
Requires-Dist: uvicorn==0.30.5
Requires-Dist: Jinja2==3.1.4
